pycommit.py
gpcli-0.1.1.dist-info/licenses/LICENCE
gpcli-0.1.1.dist-info/METADATA
gpcli-0.1.1.dist-info/WHEEL
gpcli-0.1.1.dist-info/entry_points.txt
gpcli-0.1.1.dist-info/top_level.txt
gpcli-0.1.1.dist-info/RECORD
