Metadata-Version: 2.4
Name: gpcli
Version: 0.1.1
Summary: Fast git add/commit/push via one CLI command
Author-email: Froas <froas.dev@gmail.com>
License-File: LICENCE
Dynamic: license-file
